gpt2Api_Client/GPT2License.py
gpt2Api_Client/__init__.py
gpt2Api_Client/wrapper.py
gpt2Api_Client-0.1.1.dist-info/LICENSE
gpt2Api_Client-0.1.1.dist-info/METADATA
gpt2Api_Client-0.1.1.dist-info/WHEEL
gpt2Api_Client-0.1.1.dist-info/top_level.txt
gpt2Api_Client-0.1.1.dist-info/RECORD
