Metadata-Version: 2.1
Name: gpt2Api-Client
Version: 0.1.1
Summary: Wrapper for the GPT2 Api
Home-page: UNKNOWN
Author: TechWithAnirudh (Anirudh)
Author-email: <current.address@unknown.invalid>
License: UNKNOWN
Keywords: python,gpt2,ai,api,web
Platform: UNKNOWN
Classifier: Development Status :: 1 - Planning
Classifier: Intended Audience :: Developers
Classifier: Programming Language :: Python :: 3
Classifier: Operating System :: Unix
Classifier: Operating System :: MacOS :: MacOS X
Classifier: Operating System :: Microsoft :: Windows
Requires-Dist: requests
